manga_searcher/__init__.py
manga_searcher/browser.py
manga_searcher/command_line.py
manga_searcher/db.py
manga_searcher/mal.py
manga_searcher/mangadex.py
manga_searcher/storage.py
manga_searcher-0.0.1.dist-info/LICENSE
manga_searcher-0.0.1.dist-info/METADATA
manga_searcher-0.0.1.dist-info/WHEEL
manga_searcher-0.0.1.dist-info/entry_points.txt
manga_searcher-0.0.1.dist-info/top_level.txt
manga_searcher-0.0.1.dist-info/RECORD
