Metadata-Version: 2.1
Name: manga-searcher
Version: 0.0.1
Summary: Finding new manga to read.
Home-page: https://github.com/SanteriHetekivi/manga_searcher
Author: Santeri Hetekivi
Author-email: development@hetekivi.com
Project-URL: Bug Tracker, https://github.com/SanteriHetekivi/manga_searcher/issues
Classifier: Programming Language :: Python :: 3
Classifier: License :: OSI Approved :: Apache Software License
Classifier: Operating System :: OS Independent
Requires-Python: >=3.10
License-File: LICENSE
Requires-Dist: argparse (==1.4.0)
Requires-Dist: mangadex (==2.5.2)
Requires-Dist: py-manga (==0.2.3)
Requires-Dist: typedate (==1.1.1)
Requires-Dist: myanimelist-downloader (==0.0.9)
